crocoite/__init__.py
crocoite/behavior.py
crocoite/browser.py
crocoite/cli.py
crocoite/controller.py
crocoite/devtools.py
crocoite/html.py
crocoite/irc.py
crocoite/logger.py
crocoite/test_behavior.py
crocoite/test_browser.py
crocoite/test_controller.py
crocoite/test_devtools.py
crocoite/test_html.py
crocoite/test_irc.py
crocoite/test_logger.py
crocoite/test_tools.py
crocoite/test_warc.py
crocoite/tools.py
crocoite/util.py
crocoite/warc.py
crocoite/data/canvas-snapshot.js
crocoite/data/click.js
crocoite/data/click.yaml
crocoite/data/cookies.txt
crocoite/data/extract-links.js
crocoite/data/screenshot.js
crocoite/data/scroll.js
crocoite-1.1.1.dist-info/LICENSE.txt
crocoite-1.1.1.dist-info/METADATA
crocoite-1.1.1.dist-info/WHEEL
crocoite-1.1.1.dist-info/entry_points.txt
crocoite-1.1.1.dist-info/top_level.txt
crocoite-1.1.1.dist-info/RECORD
